itaxotools/fitchi/__init__.py
itaxotools/fitchi/__main__.py
itaxotools/fitchi/fitchi.py
itaxotools/fitchi/types.py
itaxotools_fitchi-1.3.0.dist-info/LICENSE.txt
itaxotools_fitchi-1.3.0.dist-info/METADATA
itaxotools_fitchi-1.3.0.dist-info/WHEEL
itaxotools_fitchi-1.3.0.dist-info/entry_points.txt
itaxotools_fitchi-1.3.0.dist-info/top_level.txt
itaxotools_fitchi-1.3.0.dist-info/RECORD
