Metadata-Version: 2.1
Name: itaxotools-fitchi
Version: 1.3.0
Summary: Haplotype genealogies based on Fitch distances
Author-email: Michael Matschiner <michael.matschiner@nhm.uio.no>, Stefanos Patmanidis <stefanpatman91@gmail.com>
Project-URL: Homepage, https://itaxotools.org/
Project-URL: Source, https://github.com/iTaxoTools/Fitchi
Classifier: License :: OSI Approved :: GNU General Public License v3 or later (GPLv3+)
Classifier: Development Status :: 5 - Production/Stable
Classifier: Programming Language :: Python
Classifier: Programming Language :: Python :: 3.10
Classifier: Programming Language :: Python :: 3.11
Classifier: Programming Language :: Python :: 3.12
Classifier: Programming Language :: Python :: Implementation :: CPython
Requires-Python: <4,>=3.10.2
License-File: LICENSE.txt
Requires-Dist: scipy
Provides-Extra: all
Requires-Dist: pygraphviz ; extra == 'all'
Requires-Dist: biopython ; extra == 'all'
Provides-Extra: dev
Requires-Dist: setuptools-scm ; extra == 'dev'
Requires-Dist: pre-commit ; extra == 'dev'
Requires-Dist: pytest ; extra == 'dev'
